LICENSE.md
README.md
pyproject.toml
src/ewoksserver/__init__.py
src/ewoksserver/__main__.py
src/ewoksserver/config.py
src/ewoksserver/main.py
src/ewoksserver/spec.py
src/ewoksserver.egg-info/PKG-INFO
src/ewoksserver.egg-info/SOURCES.txt
src/ewoksserver.egg-info/dependency_links.txt
src/ewoksserver.egg-info/entry_points.txt
src/ewoksserver.egg-info/requires.txt
src/ewoksserver.egg-info/top_level.txt
src/ewoksserver/app/__init__.py
src/ewoksserver/app/config.py
src/ewoksserver/app/cors.py
src/ewoksserver/app/lifespan.py
src/ewoksserver/app/models.py
src/ewoksserver/app/backends/__init__.py
src/ewoksserver/app/backends/binary_backend.py
src/ewoksserver/app/backends/json_backend.py
src/ewoksserver/app/routes/__init__.py
src/ewoksserver/app/routes/backend.py
src/ewoksserver/app/routes/frontend.py
src/ewoksserver/app/routes/common/__init__.py
src/ewoksserver/app/routes/common/models.py
src/ewoksserver/app/routes/execution/__init__.py
src/ewoksserver/app/routes/execution/events.py
src/ewoksserver/app/routes/execution/models.py
src/ewoksserver/app/routes/execution/router.py
src/ewoksserver/app/routes/execution/socketio.py
src/ewoksserver/app/routes/execution/utils.py
src/ewoksserver/app/routes/icons/__init__.py
src/ewoksserver/app/routes/icons/models.py
src/ewoksserver/app/routes/icons/router.py
src/ewoksserver/app/routes/tasks/__init__.py
src/ewoksserver/app/routes/tasks/discovery.py
src/ewoksserver/app/routes/tasks/models.py
src/ewoksserver/app/routes/tasks/router.py
src/ewoksserver/app/routes/workflows/__init__.py
src/ewoksserver/app/routes/workflows/descriptions.py
src/ewoksserver/app/routes/workflows/models.py
src/ewoksserver/app/routes/workflows/router.py
src/ewoksserver/resources/__init__.py
src/ewoksserver/resources/icons/__init__.py
src/ewoksserver/resources/icons/default.png
src/ewoksserver/resources/icons/graphInput.svg
src/ewoksserver/resources/icons/graphOutput.svg
src/ewoksserver/resources/icons/sum.png
src/ewoksserver/resources/tasks/__init__.py
src/ewoksserver/resources/tasks/ewokscore.tests.examples.tasks.sumlist.SumList.json
src/ewoksserver/resources/tasks/ewokscore.tests.examples.tasks.sumtask.SumTask.json
src/ewoksserver/resources/workflows/__init__.py
