Metadata-Version: 2.4
Name: ewoksserver
Version: 2.1.1
Summary: Backend for ewoksweb
Author-email: ESRF <dau-pydev@esrf.fr>
License: # MIT License
Project-URL: Homepage, https://gitlab.esrf.fr/workflow/ewoks/ewoksserver
Project-URL: Documentation, https://workflow.gitlab-pages.esrf.fr/ewoks/ewoksserver
Project-URL: Repository, https://gitlab.esrf.fr/workflow/ewoks/ewoksserver
Project-URL: Issues, https://gitlab.esrf.fr/workflow/ewoks/ewoksserver/issues
Project-URL: Changelog, https://gitlab.esrf.fr/workflow/ewoks/ewoksserver/-/blob/main/CHANGELOG.md
Classifier: Intended Audience :: Science/Research
Classifier: License :: OSI Approved :: MIT License
Classifier: Programming Language :: Python :: 3
Requires-Python: >=3.8
License-File: LICENSE.md
Requires-Dist: fastapi
Requires-Dist: uvicorn[standard]
Requires-Dist: python-socketio
Requires-Dist: ewoksjob[worker]<2,>=1.1
Requires-Dist: ewokscore>=1.0.0
Requires-Dist: pydantic-settings
Provides-Extra: frontend
Requires-Dist: ewoksjob[sql]; extra == "frontend"
Provides-Extra: test
Requires-Dist: pytest>=7; extra == "test"
Requires-Dist: pytest-celery; extra == "test"
Requires-Dist: ewoksserver[frontend]; extra == "test"
Requires-Dist: pytest-mock; extra == "test"
Requires-Dist: httpx!=1.0.dev1; extra == "test"
Provides-Extra: dev
Requires-Dist: ewoksserver[test]; extra == "dev"
Requires-Dist: black>=25; extra == "dev"
Requires-Dist: flake8>=4; extra == "dev"
Provides-Extra: doc
Requires-Dist: ewoksserver[test]; extra == "doc"
Requires-Dist: sphinx>=4.5; extra == "doc"
Requires-Dist: sphinx-autodoc-typehints>=1.16; extra == "doc"
Requires-Dist: sphinxcontrib-redoc; extra == "doc"
Requires-Dist: sphinx_design; extra == "doc"
Requires-Dist: pydata_sphinx_theme; extra == "doc"
Dynamic: license-file
